{
	"cmake" : 
	{
		"generator" : 
		{
			"multiConfig" : false,
			"name" : "Ninja"
		},
		"paths" : 
		{
			"cmake" : "G:/Program Files/CMake/bin/cmake.exe",
			"cpack" : "G:/Program Files/CMake/bin/cpack.exe",
			"ctest" : "G:/Program Files/CMake/bin/ctest.exe",
			"root" : "G:/Program Files/CMake/share/cmake-4.3"
		},
		"version" : 
		{
			"isDirty" : false,
			"major" : 4,
			"minor" : 3,
			"patch" : 4,
			"string" : "4.3.4",
			"suffix" : ""
		}
	},
	"objects" : 
	[
		{
			"jsonFile" : "codemodel-v2-9a109c914c3aac31fcc9.json",
			"kind" : "codemodel",
			"version" : 
			{
				"major" : 2,
				"minor" : 10
			}
		},
		{
			"jsonFile" : "cache-v2-e85bccc203fd05e0e380.json",
			"kind" : "cache",
			"version" : 
			{
				"major" : 2,
				"minor" : 0
			}
		},
		{
			"jsonFile" : "cmakeFiles-v1-9ba6b9105b98d72b9f70.json",
			"kind" : "cmakeFiles",
			"version" : 
			{
				"major" : 1,
				"minor" : 1
			}
		},
		{
			"jsonFile" : "toolchains-v1-c0f7ce7ea35f02f77454.json",
			"kind" : "toolchains",
			"version" : 
			{
				"major" : 1,
				"minor" : 1
			}
		}
	],
	"reply" : 
	{
		"client-vscode" : 
		{
			"query.json" : 
			{
				"requests" : 
				[
					{
						"kind" : "cache",
						"version" : 2
					},
					{
						"kind" : "codemodel",
						"version" : 2
					},
					{
						"kind" : "toolchains",
						"version" : 1
					},
					{
						"kind" : "cmakeFiles",
						"version" : 1
					}
				],
				"responses" : 
				[
					{
						"jsonFile" : "cache-v2-e85bccc203fd05e0e380.json",
						"kind" : "cache",
						"version" : 
						{
							"major" : 2,
							"minor" : 0
						}
					},
					{
						"jsonFile" : "codemodel-v2-9a109c914c3aac31fcc9.json",
						"kind" : "codemodel",
						"version" : 
						{
							"major" : 2,
							"minor" : 10
						}
					},
					{
						"jsonFile" : "toolchains-v1-c0f7ce7ea35f02f77454.json",
						"kind" : "toolchains",
						"version" : 
						{
							"major" : 1,
							"minor" : 1
						}
					},
					{
						"jsonFile" : "cmakeFiles-v1-9ba6b9105b98d72b9f70.json",
						"kind" : "cmakeFiles",
						"version" : 
						{
							"major" : 1,
							"minor" : 1
						}
					}
				]
			}
		}
	}
}
